[
  {
    "phone": "17608748650", 
    "password": "Yang1234", 
    "device": "Android", 
    "token": "123", 
    "country": "中国", 
    "province": "云南省", 
    "city": "昆明市", # 城市  
    "address": "云南省·昆明市·五华区·在正义坊购物中心-北馆附近", 
    "latitude": " 102.7084643412781", 
    "longitude": "25.039134720956284", 
    "SERVERPUSHKEY": "SCT219325TIwuF2FAmUbTrBlReoxNVzHra", 
    "TG_BOT_TOKEN": "", 
    "TG_USER_ID": "",
    "BARK": "", 
    "PUSHPLUS": "",
    "ACCESSTOKEN": "", 
    "CORPID": "",
    "CORPSECRET": "",
    "TOUSER": "",
    "AGENTID": "",
    "THUMB_MEDIA_ID": "" ,
    "DING_PUSH_TOKEN": ""
  }
  
]
